bankstatementparser/__init__.py
bankstatementparser/bank_statement_parsers.py
bankstatementparser/camt_parser.py
bankstatementparser/cli.py
bankstatementparser/pain001_parser.py
bankstatementparser-0.0.1.dist-info/METADATA
bankstatementparser-0.0.1.dist-info/WHEEL
bankstatementparser-0.0.1.dist-info/top_level.txt
bankstatementparser-0.0.1.dist-info/RECORD
