Metadata-Version: 2.1
Name: bankstatementparser
Version: 0.0.1
Summary: BankStatementParser is your essential tool for easy bank statement management.
Home-page: https://bankstatementparser.com
Author: Sebastien Rousseau
Author-email: sebastian.rousseau@gmail.com
License: Apache Software License
Project-URL: Documentation, https://bankstatementparser.com/
Project-URL: Funding, https://paypal.me/wwdseb
Project-URL: Source, https://github.com/sebastienrousseau/bankstatementparser/releases
Keywords: banking,finance,parsing,CAMT,ISO20022,treasury,SEPA,analysis,transactions,reporting
Classifier: Development Status :: 4 - Beta
Classifier: Intended Audience :: Developers
Classifier: Intended Audience :: Financial and Insurance Industry
Classifier: License :: OSI Approved :: Apache Software License
Classifier: Operating System :: MacOS
Classifier: Operating System :: OS Independent
Classifier: Operating System :: POSIX
Classifier: Operating System :: Unix
Classifier: Programming Language :: Python :: 3.9
Classifier: Programming Language :: Python :: 3.10
Classifier: Programming Language :: Python :: 3.11
Classifier: Programming Language :: Python :: 3.12
Classifier: Programming Language :: Python
Classifier: Topic :: Software Development :: Libraries :: Python Modules
Requires-Python: >=3.9,<3.13
Requires-Dist: lxml>=4.9.3
Requires-Dist: openpyxl>=3.1.2
Requires-Dist: pandas>=2.1.1
Requires-Dist: requests>=2.31.0
